isoddeven/__init__.py
isoddeven/cli.py
isoddeven/isoddeven.py
isoddeven-1.1.0.dist-info/LICENSE
isoddeven-1.1.0.dist-info/METADATA
isoddeven-1.1.0.dist-info/WHEEL
isoddeven-1.1.0.dist-info/entry_points.txt
isoddeven-1.1.0.dist-info/top_level.txt
isoddeven-1.1.0.dist-info/RECORD
