Metadata-Version: 2.2
Name: isoddeven
Version: 1.1.0
Summary: A Python package to check if a number is odd or even.
Home-page: https://github.com/nilaysarma/isoddeven
Author: Nilay Sarma
License: MIT
Project-URL: Repository, https://github.com/nilaysarma/isoddeven
Project-URL: Release Notes, https://github.com/nilaysarma/isoddeven/releases/latest
Classifier: Development Status :: 5 - Production/Stable
Classifier: Intended Audience :: Developers
Classifier: Intended Audience :: Education
Classifier: License :: OSI Approved :: MIT License
Classifier: Operating System :: OS Independent
Classifier: Programming Language :: Python :: 3
Classifier: Topic :: Software Development :: Libraries :: Python Modules
License-File: LICENSE
Dynamic: author
Dynamic: classifier
Dynamic: description
Dynamic: description-content-type
Dynamic: home-page
Dynamic: license
Dynamic: project-url
Dynamic: summary
